agentc_langgraph/__init__.py
agentc_langgraph/agent/__init__.py
agentc_langgraph/agent/agent.py
agentc_langgraph/defaults.py
agentc_langgraph/graph/__init__.py
agentc_langgraph/graph/graph.py
agentc_langgraph/state/__init__.py
agentc_langgraph/state/checkpoint.py
agentc_langgraph/state/options.py
agentc_langgraph/tool/__init__.py
agentc_langgraph/tool/node.py
agentc_langgraph-0.2.5a2.dist-info/METADATA
agentc_langgraph-0.2.5a2.dist-info/WHEEL
agentc_langgraph-0.2.5a2.dist-info/RECORD
